{
  "patient": {
    "id": "patient-demo-001",
    "name": "Michael Rodriguez",
    "firstName": "Michael",
    "lastName": "Rodriguez",
    "dob": "1989-07-15",
    "age": 35,
    "gender": "male",
    "pronouns": "he/him",
    "mrn": "MRN-78945"
  },
  "facility": {
    "id": "facility-owensboro",
    "name": "Owensboro",
    "phone": "(270) 215-4454",
    "address": "1102 Triplett Street, Suite 2300",
    "city": "Owensboro",
    "state": "KY",
    "zip": "42303"
  },
  "provider": {
    "id": "provider-001",
    "name": "Anna Wakeland",
    "credentials": "LPCC",
    "fullName": "Anna Wakeland LPCC"
  },
  "supervisor": {
    "name": "Neil Jariwala",
    "credentials": "M.D., Psychiatrist",
    "licenseNumber": "53374",
    "licenseState": "KY"
  },
  "encounter": {
    "date": "2025-11-04",
    "time": "14:30",
    "type": "Comprehensive Biopsychosocial Intake",
    "appointmentId": "appt-demo-001"
  },
  "patient_intake": {
    "narrative": "Virtual Consult MD\nIntake Document\n\nNovember 4, 2025 â€¢ Owensboro\n\nDEMOGRAPHICS\nWhat is your first name?\nMichael\n\nWhat is your last name?\nRodriguez\n\nWhat is your date of birth?\n1989-07-15\n\nSocial Security Number?\n***-**-4521\n\nWhat is your gender identity?\nmale\n\nWhat are your pronouns?\nhe/him\n\nWhat is your race?\nhispanic\n\nWhat is your ethnicity?\nhispanic\n\nWhat is your primary language?\nenglish\n\nNeed interpreter services?\nNo\n\nPRIMARY CONCERNS\nTop concerns?\nDepression/Sadness, Trauma/PTSD symptoms, Substance use concerns, Anger/Irritability, Sleep problems\n\nWhen did these concerns start?\npast-year\n\nTriggers?\nDivorce or relationship breakup, Loss of loved one, Childhood trauma, Substance use\n\nCONTACT INFORMATION\nWhat is your phone number?\n(502) 555-7823\n\nWhat is your email address?\nmrodriguez89@email.com\n\nWhat is your street address?\n2847 Maple Ridge Drive\n\nCity?\nOwensboro\n\nState?\nKY\n\nZIP Code?\n42301\n\nEmergency Contact Name?\nMaria Rodriguez\n\nRelationship?\nSister\n\nEmergency Contact Phone?\n(502) 555-9104\n\nINSURANCE\nWhat type of insurance do you have?\nmedicaid\n\nMedicaid ID?\nKY-8745231\n\nInsurance provider?\nKentucky Medicaid (Anthem)\n\nMEDICATION ALLERGIES\nDo you have any medication allergies?\nYes\n\nMedication allergies?\nPenicillin (hives), Codeine (nausea)\n\nCURRENT MEDICATIONS\nMedication name?\nLisinopril\n\nDosage?\n10mg daily\n\nPrescribed for?\nHigh blood pressure\n\nMedication name?\nIbuprofen\n\nDosage?\n800mg as needed\n\nPrescribed for?\nChronic back pain from work injury\n\nPAST PSYCHIATRIC MEDICATIONS\nMedication name?\nZoloft (sertraline)\n\nDuration?\n6 months\n\nReason discontinued?\nDidn't feel like it was working, stopped on my own\n\nMedication name?\nTrazodone\n\nDuration?\n3 months\n\nReason discontinued?\nMade me too groggy in the morning, couldn't function at work\n\nMEDICAL CONDITIONS\nConditions you have?\nHypertension, Chronic back pain (work-related injury 2018), Type 2 Diabetes (pre-diabetic, diet controlled)\n\nSAFETY ASSESSMENT\nCurrent suicidal thoughts?\nNo, but have had thoughts in the past (6 months ago during worst of divorce)\n\nThoughts of harming others?\nNo, but struggle with anger sometimes\n\nSpecific plan for self-harm?\nNo\n\nCurrently safe?\nYes\n\nEmergency contact available?\nYes - sister Maria is very supportive\n\nCurrently in treatment?\nNo, this is first time seeking help since divorce\n\nHEALTHCARE PROVIDERS\nDo you have a primary care provider?\nYes\n\nPCP Name?\nDr. Sarah Chen\n\nPCP Practice?\nOwensboro Family Medicine\n\nPCP Phone?\n(270) 555-3200\n\nDo you have a therapist/counselor?\nNo, never been to therapy before\n\nDo you have a psychiatrist?\nNo\n\nDo you have a substance use disorder provider?\nNo, but know I need help with drinking\n\nSOCIAL & LIFESTYLE\nCurrent living arrangement?\nLiving alone in apartment\n\nHousing stability?\nStable for now, but rent is expensive and finances are tight\n\nRelationship status?\nDivorced (finalized 8 months ago)\n\nChildren?\nTwo daughters, ages 8 and 11, see them every other weekend\n\nSocial support network?\nLimited - sister is main support, lost most friends during marriage/divorce\n\nEmployment status?\nFull-time warehouse supervisor\n\nEmployer?\nAmazon Fulfillment Center\n\nHighest education completed?\nHigh school diploma, some college (didn't finish)\n\nFinancial stress level?\nVery high - child support, legal fees from divorce, medical bills from back injury\n\nMilitary service?\nNo\n\nLegal issues?\nDUI 14 months ago (during separation), completed probation\n\nSUBSTANCE USE\nDo you smoke or use tobacco?\nYes, about half pack per day (trying to cut back)\n\nHow often do you drink alcohol?\nDaily, especially on weekends\n\nDrinks per occasion?\n4-6 beers on weeknights, 8-10 on weekends\n\nConcerns about drinking?\nYes - know it's gotten worse since divorce, using it to cope with stress and loneliness\n\nHave you used recreational drugs in the past year?\nMarijuana occasionally (2-3 times per month), used cocaine during marriage but stopped after DUI\n\nSubstance use history?\nStarted drinking heavily in early 20s, was worse during marriage (wife also drank heavily), got DUI during separation, trying to cut back but struggling\n\nFAMILY HISTORY\nFamily mental health history?\nFather had depression and alcoholism (died age 58 from liver disease), mother has anxiety, brother has PTSD from military service\n\nFamily substance use history?\nFather was alcoholic, uncle on mother's side had drug problems\n\nTRAUMA HISTORY\nChildhood trauma?\nWitnessed significant domestic violence between parents (father would get drunk and violent), felt responsible for protecting younger siblings, moved around a lot due to financial instability\n\nAdult trauma?\nWork injury in 2018 (fell from forklift, chronic back pain since), emotionally abusive marriage, contentious divorce, lost custody battle for primary placement of daughters\n\nWORK/DAILY FUNCTIONING\nHow is work affected by symptoms?\nCalling in sick more often (used 8 sick days in past 3 months), trouble concentrating on tasks, irritable with coworkers, worried about losing job\n\nHow are relationships affected?\nDivorced, limited contact with daughters (hurts deeply), pushed away friends, arguing with sister more, isolated and lonely\n\nHow is self-care affected?\nNot eating regularly, sleep is terrible (3-4 hours per night), apartment is messy, not exercising, drinking too much, smoking more\n\nHOBBIES & INTERESTS (BEFORE SYMPTOMS)\nUsed to enjoy:\n- Coaching daughters' soccer team\n- Working on cars (had old Mustang project car, had to sell during divorce)\n- Fishing with friends\n- Playing guitar\n\nNow:\nDon't do any of these anymore, no motivation, just work and drink\n\nGOALS FOR TREATMENT\n1. Stop feeling so angry and depressed all the time\n2. Get my drinking under control before I lose my job or get another DUI\n3. Be a better father - want my daughters to see me as stable and healthy\n4. Deal with what happened in my childhood and marriage\n5. Sleep better and have energy again\n\nSTRENGTHS\n- Hard worker, good work ethic despite current struggles\n- Love my daughters deeply, want to be better for them\n- Sister is supportive\n- Recognizing I need help (took courage to come here)\n- Physically strong despite back pain\n- Good at problem-solving when not overwhelmed",
    "structured": {
      "demographics": {
        "firstName": "Michael",
        "lastName": "Rodriguez",
        "dob": "1989-07-15",
        "ssn": "***-**-4521",
        "gender": "male",
        "pronouns": "he/him",
        "race": "hispanic",
        "ethnicity": "hispanic",
        "primaryLanguage": "english",
        "interpreterNeeded": false
      },
      "primaryConcerns": [
        "Depression/Sadness",
        "Trauma/PTSD symptoms",
        "Substance use concerns",
        "Anger/Irritability",
        "Sleep problems"
      ],
      "concernOnset": "past-year",
      "triggers": [
        "Divorce or relationship breakup",
        "Loss of loved one",
        "Childhood trauma",
        "Substance use"
      ],
      "substanceUse": {
        "tobacco": "daily (half pack)",
        "alcohol": "daily, 4-6 beers weeknights, 8-10 weekends",
        "concernsAboutDrinking": true,
        "marijuana": "2-3 times per month",
        "pastCocaineUse": true,
        "duiHistory": "14 months ago"
      },
      "medicalHistory": {
        "conditions": ["Hypertension", "Chronic back pain (work injury 2018)", "Pre-diabetes"],
        "allergies": ["Penicillin (hives)", "Codeine (nausea)"],
        "currentMedications": [
          {"name": "Lisinopril", "dosage": "10mg daily", "for": "High blood pressure"},
          {"name": "Ibuprofen", "dosage": "800mg PRN", "for": "Chronic back pain"}
        ],
        "pastPsychMeds": ["Zoloft", "Trazodone"]
      },
      "socialHistory": {
        "living": "Alone in apartment",
        "housingStability": "Stable but financially tight",
        "relationshipStatus": "Divorced (8 months)",
        "children": "Two daughters ages 8 and 11, every other weekend",
        "employment": "Full-time warehouse supervisor at Amazon",
        "education": "High school, some college (incomplete)",
        "financialStress": "Very high",
        "supportNetwork": "Limited, sister is main support"
      },
      "familyHistory": {
        "mentalHealth": "Father: depression and alcoholism (died age 58), Mother: anxiety, Brother: PTSD",
        "substanceUse": "Father: alcoholic, Uncle: drug problems"
      },
      "traumaHistory": {
        "childhood": "Witnessed domestic violence, protected siblings, financial instability",
        "adult": "Work injury 2018, emotionally abusive marriage, contentious divorce, custody loss"
      },
      "providers": {
        "pcp": {
          "name": "Dr. Sarah Chen",
          "practice": "Owensboro Family Medicine",
          "phone": "(270) 555-3200"
        }
      }
    }
  },
  "clinical_intake": {
    "qaText": "=== CLINICAL INTAKE RESPONSES ===\nGenerated: 11/04/2025, 2:30:00 PM\n\n## CHIEF COMPLAINT\nQ: What brings you in today? (Chief complaint)\nA: Everything fell apart after my divorce. I'm drinking too much, can't sleep, angry all the time. My daughters deserve a better dad than what I've been lately.\n\n## CURRENT SYMPTOMS & IMPACT\nQ: How are symptoms impacting your work/school?\nA: Severe impact - called in sick 8 times in 3 months, trouble concentrating, irritable with coworkers, worried about losing job\n\nQ: How are symptoms impacting your relationships?\nA: Severe impact - divorced, limited time with daughters, pushed away friends, arguing with sister, very isolated\n\nQ: How are symptoms impacting your self-care?\nA: Severe impact - not eating regularly, sleeping 3-4 hours, apartment messy, drinking daily, smoking more\n\nQ: How are symptoms impacting your social life?\nA: Severe impact - completely isolated, no friends, don't do hobbies anymore, just work and drink\n\nQ: Current stress level (1-10)?\nA: 9/10\n\nQ: How would you rate your sleep quality?\nA: Very poor - 3-4 hours per night, wake up multiple times, racing thoughts about divorce and daughters\n\nQ: How many days have you missed from work/school in the past month?\nA: 3 days\n\n## DAILY LIFE & SELF-CARE\nQ: How structured is your daily routine?\nA: Very unstructured - work schedule is only consistent thing, everything else is chaotic\n\nQ: What self-care challenges are you facing?\nA: Not eating regular meals (maybe once a day), no exercise since back injury, apartment is cluttered and dirty, personal hygiene suffering some days, drinking to cope every night\n\nQ: Describe your typical sleep schedule\nA: Try to sleep around midnight, wake up 2-3am and can't fall back asleep, thoughts racing about divorce and daughters, get up exhausted around 6am for work\n\nQ: How do you cope with difficult emotions currently?\nA: Drinking, smoking, isolating myself, sometimes punch walls when really angry (never hurt anyone)\n\n## GOALS & STRENGTHS\nQ: What are your top 3 treatment goals?\nA: Get drinking under control before I lose my job or get another DUI, be a better father for my daughters, stop feeling so angry and depressed all the time\n\nQ: What personal strengths can you build on?\nA: Hard worker even when struggling, love my daughters more than anything, sister supports me, I know I need help and came here\n\nQ: On a scale of 1-10, how motivated are you for change?\nA: 8/10 - I'm scared of losing everything, especially my daughters\n\nQ: What has prevented you from getting help before?\nA: Thought I could handle it myself, stigma about therapy (didn't grow up with that being okay), cost, didn't think I deserved help\n\n## DIAGNOSES\nDiagnosis 1:\nQ: Diagnosis code (ICD-10/DSM-5)\nA: F33.2\n\nQ: Diagnosis description\nA: Major Depressive Disorder, Severe\n\nDiagnosis 2:\nQ: Diagnosis code (ICD-10/DSM-5)\nA: F43.10\n\nQ: Diagnosis description\nA: Post-Traumatic Stress Disorder\n\nDiagnosis 3:\nQ: Diagnosis code (ICD-10/DSM-5)\nA: F10.20\n\nQ: Diagnosis description\nA: Alcohol Use Disorder, Severe\n\n## TREATMENT HISTORY\nTreatment 1:\nQ: Type of treatment\nA: Mental Health (tried Zoloft 6 months, didn't complete treatment, stopped on own)\n\nTreatment 2:\nQ: Type of treatment\nA: Substance Use (completed DUI classes and probation, but no formal SUD treatment)\n\n## MEDICATIONS (CLINICIAN-VERIFIED)\nQ: Current medications (clinician-verified)\nA: Lisinopril 10mg daily (hypertension), Ibuprofen 800mg PRN (chronic back pain)\n\nQ: Previously trialed psychiatric medications\nA: Zoloft (sertraline) 50mg for 6 months - patient reports \"didn't feel like it was working\" and discontinued on his own without tapering. Trazodone 50mg for sleep for 3 months - discontinued due to morning grogginess that interfered with work functioning.\n\n## MENTAL STATUS EXAMINATION\nQ: Appearance and presentation\nA: Casually dressed in work clothes (Amazon uniform), appears slightly older than stated age, poor grooming (unshaven, disheveled hair), appears fatigued\n\nQ: Behavior and activity level\nA: Cooperative but guarded initially, fidgeting with hands, poor eye contact, becomes tearful when discussing daughters\n\nQ: Speech pattern and quality\nA: Normal rate and volume, but monotone affect in voice, occasional long pauses before answering emotionally difficult questions\n\nQ: Stated mood\nA: \"Depressed, angry, exhausted\"\n\nQ: Observed affect\nA: Constricted and dysphoric, briefly tearful when discussing children, flattened overall with occasional flashes of irritability\n\nQ: Thought process/organization\nA: Linear and goal-directed, no flight of ideas, coherent but occasionally tangential when discussing trauma history\n\nQ: Thought content\nA: Denies current suicidal ideation but endorses passive thoughts 6 months ago (\"thought everyone would be better off without me\"), no current plan or intent. Denies homicidal ideation but acknowledges anger control issues (\"I punch walls, never people\"). Significant guilt about divorce and impact on daughters. Rumination about past mistakes.\n\nQ: Perceptual disturbances (hallucinations/illusions)\nA: Denies hallucinations. Reports occasional intrusive memories/flashbacks of childhood domestic violence and work injury. Hypervigilance noted (\"always waiting for something bad to happen\").\n\nQ: Cognitive functioning and orientation\nA: Alert and oriented x4 (person, place, time, situation). Attention somewhat impaired by depressive symptoms and sleep deprivation. Memory appears intact for recent and remote events. Concentration impaired - reports difficulty at work with multi-step tasks.\n\nQ: Level of insight\nA: Fair to good - recognizes he needs help, acknowledges drinking is problematic, understands connection between childhood trauma and current struggles, motivated to change for daughters\n\nQ: Quality of judgment\nA: Currently fair - seeking treatment is positive, but recent judgment impaired by substance use (DUI 14 months ago, continued heavy drinking despite consequences). Understands risks but struggles to implement changes.\n\nQ: Clinical Impressions\nA: Patient presents with severe depression complicated by untreated PTSD from childhood trauma and recent life stressors, alongside severe alcohol use disorder that patient is using as maladaptive coping mechanism. The interplay between these conditions is significant - childhood domestic violence exposure has created trauma response patterns that are triggered by his own divorce and family disruption. His alcohol use, while initially providing temporary relief from depression and PTSD symptoms, is now exacerbating his mental health decline and creating additional stressors (DUI, work performance issues, financial strain). Assessment scores confirm severe depression (PHQ-9: 21), moderate-to-severe PTSD symptoms (PCL-5: 52), and severe alcohol use disorder (AUDIT: 28). High ACE score (6/10) indicates significant childhood adversity contributing to current presentation. Patient's insight and motivation are protective factors, as is his deep love for his daughters and relationship with supportive sister. Immediate risks include job loss, another DUI, worsening physical health from alcohol use, and potential suicide risk if depression continues to worsen. Patient requires integrated treatment addressing mental health and substance use simultaneously.\n\nQ: Clinical Recommendations\nA: Recommend comprehensive integrated treatment approach including: 1) Psychiatric evaluation for medication management - consider SSRI trial (patient discontinued Zoloft prematurely, may benefit from adequate trial at therapeutic dose with proper monitoring) and possible adjunct medication for sleep given severe insomnia, 2) Individual trauma-focused therapy (EMDR or CPT) to address childhood trauma and PTSD symptoms, 3) Substance use treatment - recommend intensive outpatient program (IOP) given severity of alcohol use disorder and need for structured support, include relapse prevention planning, 4) Case management for care coordination and resource connection, 5) Possible short-term medical leave from work to focus on stabilization if symptoms continue to impair functioning, 6) Safety planning given past suicidal ideation - establish crisis resources and check-ins, 7) Encourage engagement with peer support (AA or SMART Recovery) for substance use recovery, 8) Family therapy or parenting support to improve relationship with daughters and address guilt. Priority is stabilizing substance use and depression to prevent further deterioration and potential safety crisis.\n\n=== END OF CLINICAL INTAKE ===",
    "structured": {
      "chiefComplaint": "Everything fell apart after my divorce. I'm drinking too much, can't sleep, angry all the time. My daughters deserve a better dad than what I've been lately.",
      "currentSymptoms": {
        "workImpact": "severe",
        "relationshipImpact": "severe",
        "selfCareImpact": "severe",
        "socialLifeImpact": "severe",
        "stressLevel": 9,
        "sleepQuality": "very poor",
        "missedWorkDays": 3
      },
      "dailyLife": {
        "routineStructure": "very unstructured",
        "selfCareChallenges": "not eating regularly, no exercise, cluttered apartment, hygiene suffering, drinking to cope",
        "sleepSchedule": "midnight to 2-3am, racing thoughts, wake exhausted 6am",
        "copingMechanisms": "drinking, smoking, isolating, punching walls when angry"
      },
      "goalsStrengths": {
        "goals": [
          "Get drinking under control before losing job or another DUI",
          "Be a better father for daughters",
          "Stop feeling so angry and depressed"
        ],
        "strengths": [
          "Hard worker despite struggles",
          "Deep love for daughters",
          "Sister's support",
          "Recognition of need for help"
        ],
        "motivation": 8,
        "barriers": "Thought could handle alone, stigma, cost, didn't think deserved help"
      },
      "diagnoses": [
        {
          "code": "F33.2",
          "description": "Major Depressive Disorder, Severe"
        },
        {
          "code": "F43.10",
          "description": "Post-Traumatic Stress Disorder"
        },
        {
          "code": "F10.20",
          "description": "Alcohol Use Disorder, Severe"
        }
      ],
      "treatmentHistory": [
        {
          "type": "Mental Health",
          "details": "Tried Zoloft 6 months, discontinued on own"
        },
        {
          "type": "Substance Use",
          "details": "Completed DUI classes and probation, no formal SUD treatment"
        }
      ],
      "medications": {
        "current": "Lisinopril 10mg daily, Ibuprofen 800mg PRN",
        "previousPsych": "Zoloft 50mg 6 months (stopped on own, felt ineffective), Trazodone 50mg 3 months (morning grogginess)"
      },
      "mse": {
        "appearance": "Casually dressed in work clothes, appears older than age, poor grooming, fatigued",
        "behavior": "Cooperative but guarded, fidgeting, poor eye contact, tearful discussing daughters",
        "speech": "Normal rate and volume, monotone, occasional long pauses",
        "mood": "Depressed, angry, exhausted",
        "affect": "Constricted and dysphoric, briefly tearful, flattened with occasional irritability",
        "thoughtProcess": "Linear and goal-directed, occasionally tangential with trauma",
        "thoughtContent": "Denies current SI, past passive thoughts 6mo ago, no HI, anger control issues, significant guilt, rumination",
        "perceptualDisturbances": "No hallucinations, intrusive memories/flashbacks of childhood DV and work injury, hypervigilance",
        "cognition": "Alert and oriented x4, attention impaired by depression/sleep deprivation, memory intact, concentration impaired",
        "insight": "Fair to good - recognizes need for help, acknowledges drinking problem, understands trauma connection",
        "judgment": "Currently fair - seeking treatment positive, but impaired by substance use, understands risks"
      },
      "clinicalImpressions": "Patient presents with severe depression complicated by untreated PTSD from childhood trauma and recent life stressors, alongside severe alcohol use disorder that patient is using as maladaptive coping mechanism. The interplay between these conditions is significant - childhood domestic violence exposure has created trauma response patterns that are triggered by his own divorce and family disruption. His alcohol use, while initially providing temporary relief from depression and PTSD symptoms, is now exacerbating his mental health decline and creating additional stressors (DUI, work performance issues, financial strain). Assessment scores confirm severe depression (PHQ-9: 21), moderate-to-severe PTSD symptoms (PCL-5: 52), and severe alcohol use disorder (AUDIT: 28). High ACE score (6/10) indicates significant childhood adversity contributing to current presentation. Patient's insight and motivation are protective factors, as is his deep love for his daughters and relationship with supportive sister. Immediate risks include job loss, another DUI, worsening physical health from alcohol use, and potential suicide risk if depression continues to worsen. Patient requires integrated treatment addressing mental health and substance use simultaneously.",
      "clinicalRecommendations": "Recommend comprehensive integrated treatment approach including: 1) Psychiatric evaluation for medication management - consider SSRI trial (patient discontinued Zoloft prematurely, may benefit from adequate trial at therapeutic dose with proper monitoring) and possible adjunct medication for sleep given severe insomnia, 2) Individual trauma-focused therapy (EMDR or CPT) to address childhood trauma and PTSD symptoms, 3) Substance use treatment - recommend intensive outpatient program (IOP) given severity of alcohol use disorder and need for structured support, include relapse prevention planning, 4) Case management for care coordination and resource connection, 5) Possible short-term medical leave from work to focus on stabilization if symptoms continue to impair functioning, 6) Safety planning given past suicidal ideation - establish crisis resources and check-ins, 7) Encourage engagement with peer support (AA or SMART Recovery) for substance use recovery, 8) Family therapy or parenting support to improve relationship with daughters and address guilt. Priority is stabilizing substance use and depression to prevent further deterioration and potential safety crisis."
    }
  },
  "assessments": {
    "phq9": {
      "title": "PHQ-9 (Patient Health Questionnaire-9)",
      "completedDate": "2025-11-04",
      "totalScore": 21,
      "maxScore": 27,
      "severity": "Severe depression",
      "responses": [
        {
          "number": 1,
          "question": "Little interest or pleasure in doing things",
          "answer": "Nearly every day",
          "score": 3
        },
        {
          "number": 2,
          "question": "Feeling down, depressed, or hopeless",
          "answer": "Nearly every day",
          "score": 3
        },
        {
          "number": 3,
          "question": "Trouble falling/staying asleep, or sleeping too much",
          "answer": "Nearly every day",
          "score": 3
        },
        {
          "number": 4,
          "question": "Feeling tired or having little energy",
          "answer": "Nearly every day",
          "score": 3
        },
        {
          "number": 5,
          "question": "Poor appetite or overeating",
          "answer": "More than half the days",
          "score": 2
        },
        {
          "number": 6,
          "question": "Feeling bad about yourself - or that you are a failure or have let yourself or your family down",
          "answer": "Nearly every day",
          "score": 3
        },
        {
          "number": 7,
          "question": "Trouble concentrating on things, such as reading the newspaper or watching television",
          "answer": "More than half the days",
          "score": 2
        },
        {
          "number": 8,
          "question": "Moving or speaking so slowly that other people could have noticed, or the opposite - being so fidgety or restless that you have been moving around a lot more than usual",
          "answer": "Several days",
          "score": 1
        },
        {
          "number": 9,
          "question": "Thoughts that you would be better off dead, or of hurting yourself in some way",
          "answer": "Several days",
          "score": 1
        }
      ],
      "interpretation": "Score of 21 indicates severe depression. Patient endorses nearly daily anhedonia, depressed mood, insomnia, fatigue, guilt/worthlessness, with several days of passive suicidal ideation. Immediate clinical attention warranted."
    },
    "gad7": {
      "title": "GAD-7 (Generalized Anxiety Disorder-7)",
      "completedDate": "2025-11-04",
      "totalScore": 14,
      "maxScore": 21,
      "severity": "Moderate anxiety",
      "responses": [
        {
          "number": 1,
          "question": "Feeling nervous, anxious, or on edge",
          "answer": "More than half the days",
          "score": 2
        },
        {
          "number": 2,
          "question": "Not being able to stop or control worrying",
          "answer": "More than half the days",
          "score": 2
        },
        {
          "number": 3,
          "question": "Worrying too much about different things",
          "answer": "Nearly every day",
          "score": 3
        },
        {
          "number": 4,
          "question": "Trouble relaxing",
          "answer": "Nearly every day",
          "score": 3
        },
        {
          "number": 5,
          "question": "Being so restless that it's hard to sit still",
          "answer": "Several days",
          "score": 1
        },
        {
          "number": 6,
          "question": "Becoming easily annoyed or irritable",
          "answer": "Nearly every day",
          "score": 3
        },
        {
          "number": 7,
          "question": "Feeling afraid as if something awful might happen",
          "answer": "Not at all",
          "score": 0
        }
      ],
      "interpretation": "Score of 14 indicates moderate anxiety. Patient reports frequent worry, difficulty relaxing, and significant irritability. Anxiety likely related to PTSD hypervigilance and current life stressors."
    },
    "ace": {
      "title": "ACE (Adverse Childhood Experiences)",
      "completedDate": "2025-11-04",
      "totalScore": 6,
      "maxScore": 10,
      "severity": "High adverse childhood experiences",
      "responses": [
        {
          "number": 1,
          "question": "Did a parent or other adult in the household often or very often swear at you, insult you, put you down, or humiliate you?",
          "answer": "Yes"
        },
        {
          "number": 2,
          "question": "Did a parent or other adult in the household often or very often push, grab, slap, or throw something at you, or ever hit you so hard that you had marks or were injured?",
          "answer": "Yes"
        },
        {
          "number": 3,
          "question": "Did an adult or person at least 5 years older than you ever touch or fondle you or have you touch their body in a sexual way, or attempt or actually have oral, anal, or vaginal intercourse with you?",
          "answer": "No"
        },
        {
          "number": 4,
          "question": "Did you often or very often feel that no one in your family loved you or thought you were important or special?",
          "answer": "Yes"
        },
        {
          "number": 5,
          "question": "Did you often or very often feel that your family didn't look out for each other, feel close to each other, or support each other?",
          "answer": "Yes"
        },
        {
          "number": 6,
          "question": "Were your parents ever separated or divorced?",
          "answer": "No"
        },
        {
          "number": 7,
          "question": "Was your mother or stepmother often or very often pushed, grabbed, slapped, or had something thrown at her, or sometimes, often, or very often kicked, bitten, hit with a fist, or hit with something hard?",
          "answer": "Yes"
        },
        {
          "number": 8,
          "question": "Did you live with anyone who was a problem drinker or alcoholic, or who used street drugs?",
          "answer": "Yes"
        },
        {
          "number": 9,
          "question": "Was a household member depressed or mentally ill, or did a household member attempt suicide?",
          "answer": "No"
        },
        {
          "number": 10,
          "question": "Did a household member go to prison?",
          "answer": "No"
        }
      ],
      "interpretation": "Score of 6 out of 10 indicates high adverse childhood experiences. Patient endorses emotional abuse, physical abuse, emotional neglect, household dysfunction (domestic violence, substance abuse). ACE scores of 4+ are associated with significantly increased risk for depression, substance use disorders, and PTSD in adulthood. Patient's current presentation is consistent with research on high ACE scores and their long-term mental health impacts."
    },
    "audit": {
      "title": "AUDIT (Alcohol Use Disorders Identification Test)",
      "completedDate": "2025-11-04",
      "totalScore": 28,
      "maxScore": 40,
      "severity": "Severe alcohol use disorder - high risk",
      "responses": [
        {
          "number": 1,
          "question": "How often do you have a drink containing alcohol?",
          "answer": "4 or more times a week",
          "score": 4
        },
        {
          "number": 2,
          "question": "How many drinks containing alcohol do you have on a typical day when you are drinking?",
          "answer": "7-9",
          "score": 3
        },
        {
          "number": 3,
          "question": "How often do you have six or more drinks on one occasion?",
          "answer": "Daily or almost daily",
          "score": 4
        },
        {
          "number": 4,
          "question": "How often during the last year have you found that you were not able to stop drinking once you had started?",
          "answer": "Daily or almost daily",
          "score": 4
        },
        {
          "number": 5,
          "question": "How often during the last year have you failed to do what was normally expected of you because of drinking?",
          "answer": "Weekly",
          "score": 3
        },
        {
          "number": 6,
          "question": "How often during the last year have you needed a first drink in the morning to get yourself going after a heavy drinking session?",
          "answer": "Monthly",
          "score": 2
        },
        {
          "number": 7,
          "question": "How often during the last year have you had a feeling of guilt or remorse after drinking?",
          "answer": "Daily or almost daily",
          "score": 4
        },
        {
          "number": 8,
          "question": "How often during the last year have you been unable to remember what happened the night before because of your drinking?",
          "answer": "Weekly",
          "score": 2
        },
        {
          "number": 9,
          "question": "Have you or someone else been injured because of your drinking?",
          "answer": "Yes, but not in the last year",
          "score": 2
        },
        {
          "number": 10,
          "question": "Has a relative, friend, doctor, or other health care worker been concerned about your drinking or suggested you cut down?",
          "answer": "Yes, during the last year",
          "score": 4
        }
      ],
      "interpretation": "Score of 28 indicates severe alcohol use disorder with high risk for alcohol-related harm. Patient reports daily drinking with inability to stop, frequent binge drinking (6+ drinks), daily guilt, weekly blackouts, and negative consequences (work performance, DUI). Morning drinking occasionally present suggesting physical dependence. Sister and healthcare worker have expressed concern. Patient requires comprehensive substance use treatment and medical evaluation for withdrawal risk."
    },
    "dast10": {
      "title": "DAST-10 (Drug Abuse Screening Test)",
      "completedDate": "2025-11-04",
      "totalScore": 3,
      "maxScore": 10,
      "severity": "Low to moderate substance use concerns",
      "responses": [
        {
          "number": 1,
          "question": "Have you used drugs other than those required for medical reasons?",
          "answer": "Yes - marijuana currently, cocaine in past",
          "score": 1
        },
        {
          "number": 2,
          "question": "Do you abuse more than one drug at a time?",
          "answer": "No - only marijuana now, stopped cocaine after DUI",
          "score": 0
        },
        {
          "number": 3,
          "question": "Are you unable to stop using drugs when you want to?",
          "answer": "No - able to stop cocaine, marijuana is occasional",
          "score": 0
        },
        {
          "number": 4,
          "question": "Have you ever had blackouts or flashbacks as a result of drug use?",
          "answer": "No",
          "score": 0
        },
        {
          "number": 5,
          "question": "Do you ever feel bad or guilty about your drug use?",
          "answer": "Yes - felt guilty about cocaine use during marriage",
          "score": 1
        },
        {
          "number": 6,
          "question": "Does your spouse (or parents) ever complain about your involvement with drugs?",
          "answer": "Yes - ex-wife complained about cocaine use",
          "score": 1
        },
        {
          "number": 7,
          "question": "Have you neglected your family because of your use of drugs?",
          "answer": "No",
          "score": 0
        },
        {
          "number": 8,
          "question": "Have you engaged in illegal activities in order to obtain drugs?",
          "answer": "No",
          "score": 0
        },
        {
          "number": 9,
          "question": "Have you ever experienced withdrawal symptoms (felt sick) when you stopped taking drugs?",
          "answer": "No",
          "score": 0
        },
        {
          "number": 10,
          "question": "Have you had medical problems as a result of your drug use?",
          "answer": "No",
          "score": 0
        }
      ],
      "interpretation": "Score of 3 indicates low to moderate substance use concerns. Patient reports past cocaine use (discontinued after DUI), current occasional marijuana use (2-3x/month). While current drug use is less problematic than alcohol, history suggests polysubstance use pattern during periods of high stress. Patient demonstrates ability to discontinue substances (cocaine), which is protective factor. Primary substance use concern is severe alcohol use disorder."
    }
  }
}
